{"nodes": [{"id": "c_users_vishw_desktop_evokeeduglobal_src_features_admin_components_responsive_admin_wrapper_tsx", "label": "responsive-admin-wrapper.tsx", "file_type": "code", "source_file": "C:\\Users\\vishw\\Desktop\\evokeeduglobal\\src\\features\\admin\\components\\responsive-admin-wrapper.tsx", "source_location": "L1"}, {"id": "responsive_admin_wrapper_responsiveadminwrapper", "label": "ResponsiveAdminWrapper()", "file_type": "code", "source_file": "C:\\Users\\vishw\\Desktop\\evokeeduglobal\\src\\features\\admin\\components\\responsive-admin-wrapper.tsx", "source_location": "L32"}], "edges": [{"source": "c_users_vishw_desktop_evokeeduglobal_src_features_admin_components_responsive_admin_wrapper_tsx", "target": "react", "relation": "imports_from", "confidence": "EXTRACTED", "source_file": "C:\\Users\\vishw\\Desktop\\evokeeduglobal\\src\\features\\admin\\components\\responsive-admin-wrapper.tsx", "source_location": "L6", "weight": 1.0}, {"source": "c_users_vishw_desktop_evokeeduglobal_src_features_admin_components_responsive_admin_wrapper_tsx", "target": "card", "relation": "imports_from", "confidence": "EXTRACTED", "source_file": "C:\\Users\\vishw\\Desktop\\evokeeduglobal\\src\\features\\admin\\components\\responsive-admin-wrapper.tsx", "source_location": "L7", "weight": 1.0}, {"source": "c_users_vishw_desktop_evokeeduglobal_src_features_admin_components_responsive_admin_wrapper_tsx", "target": "skeleton", "relation": "imports_from", "confidence": "EXTRACTED", "source_file": "C:\\Users\\vishw\\Desktop\\evokeeduglobal\\src\\features\\admin\\components\\responsive-admin-wrapper.tsx", "source_location": "L14", "weight": 1.0}, {"source": "c_users_vishw_desktop_evokeeduglobal_src_features_admin_components_responsive_admin_wrapper_tsx", "target": "use_media_query", "relation": "imports_from", "confidence": "EXTRACTED", "source_file": "C:\\Users\\vishw\\Desktop\\evokeeduglobal\\src\\features\\admin\\components\\responsive-admin-wrapper.tsx", "source_location": "L15", "weight": 1.0}, {"source": "c_users_vishw_desktop_evokeeduglobal_src_features_admin_components_responsive_admin_wrapper_tsx", "target": "responsive_admin_wrapper_responsiveadminwrapper", "relation": "contains", "confidence": "EXTRACTED", "source_file": "C:\\Users\\vishw\\Desktop\\evokeeduglobal\\src\\features\\admin\\components\\responsive-admin-wrapper.tsx", "source_location": "L32", "weight": 1.0}], "raw_calls": [{"caller_nid": "responsive_admin_wrapper_responsiveadminwrapper", "callee": "useMediaQuery", "source_file": "C:\\Users\\vishw\\Desktop\\evokeeduglobal\\src\\features\\admin\\components\\responsive-admin-wrapper.tsx", "source_location": "L45"}]}