{"nodes": [{"id": "src_features_student_components_dashboard_weekly_activity_chart_tsx", "label": "weekly-activity-chart.tsx", "file_type": "code", "source_file": "src\\features\\student\\components\\dashboard\\weekly-activity-chart.tsx", "source_location": "L1"}, {"id": "weekly_activity_chart_weeklyactivitychart", "label": "WeeklyActivityChart()", "file_type": "code", "source_file": "src\\features\\student\\components\\dashboard\\weekly-activity-chart.tsx", "source_location": "L31"}, {"id": "weekly_activity_chart_weeklyactivitychartskeleton", "label": "WeeklyActivityChartSkeleton()", "file_type": "code", "source_file": "src\\features\\student\\components\\dashboard\\weekly-activity-chart.tsx", "source_location": "L102"}], "edges": [{"source": "src_features_student_components_dashboard_weekly_activity_chart_tsx", "target": "recharts", "relation": "imports_from", "confidence": "EXTRACTED", "source_file": "src\\features\\student\\components\\dashboard\\weekly-activity-chart.tsx", "source_location": "L3", "weight": 1.0}, {"source": "src_features_student_components_dashboard_weekly_activity_chart_tsx", "target": "card", "relation": "imports_from", "confidence": "EXTRACTED", "source_file": "src\\features\\student\\components\\dashboard\\weekly-activity-chart.tsx", "source_location": "L4", "weight": 1.0}, {"source": "src_features_student_components_dashboard_weekly_activity_chart_tsx", "target": "chart", "relation": "imports_from", "confidence": "EXTRACTED", "source_file": "src\\features\\student\\components\\dashboard\\weekly-activity-chart.tsx", "source_location": "L11", "weight": 1.0}, {"source": "src_features_student_components_dashboard_weekly_activity_chart_tsx", "target": "skeleton", "relation": "imports_from", "confidence": "EXTRACTED", "source_file": "src\\features\\student\\components\\dashboard\\weekly-activity-chart.tsx", "source_location": "L17", "weight": 1.0}, {"source": "src_features_student_components_dashboard_weekly_activity_chart_tsx", "target": "dashboard", "relation": "imports_from", "confidence": "EXTRACTED", "source_file": "src\\features\\student\\components\\dashboard\\weekly-activity-chart.tsx", "source_location": "L18", "weight": 1.0}, {"source": "src_features_student_components_dashboard_weekly_activity_chart_tsx", "target": "weekly_activity_chart_weeklyactivitychart", "relation": "contains", "confidence": "EXTRACTED", "source_file": "src\\features\\student\\components\\dashboard\\weekly-activity-chart.tsx", "source_location": "L31", "weight": 1.0}, {"source": "src_features_student_components_dashboard_weekly_activity_chart_tsx", "target": "weekly_activity_chart_weeklyactivitychartskeleton", "relation": "contains", "confidence": "EXTRACTED", "source_file": "src\\features\\student\\components\\dashboard\\weekly-activity-chart.tsx", "source_location": "L102", "weight": 1.0}], "raw_calls": [{"caller_nid": "weekly_activity_chart_weeklyactivitychart", "callee": "reduce", "source_file": "src\\features\\student\\components\\dashboard\\weekly-activity-chart.tsx", "source_location": "L32"}]}