{"nodes": [{"id": "c_users_vishw_desktop_evokeeduglobal_src_lib_live_stream_go_live_orchestrator_ts", "label": "go-live-orchestrator.ts", "file_type": "code", "source_file": "C:\\Users\\vishw\\Desktop\\evokeeduglobal\\src\\lib\\live-stream\\go-live-orchestrator.ts", "source_location": "L1"}, {"id": "go_live_orchestrator_ensureyoutubebroadcast", "label": "ensureYouTubeBroadcast()", "file_type": "code", "source_file": "C:\\Users\\vishw\\Desktop\\evokeeduglobal\\src\\lib\\live-stream\\go-live-orchestrator.ts", "source_location": "L7"}, {"id": "go_live_orchestrator_transitionyoutubelive", "label": "transitionYouTubeLive()", "file_type": "code", "source_file": "C:\\Users\\vishw\\Desktop\\evokeeduglobal\\src\\lib\\live-stream\\go-live-orchestrator.ts", "source_location": "L27"}, {"id": "go_live_orchestrator_endyoutubestream", "label": "endYouTubeStream()", "file_type": "code", "source_file": "C:\\Users\\vishw\\Desktop\\evokeeduglobal\\src\\lib\\live-stream\\go-live-orchestrator.ts", "source_location": "L37"}, {"id": "go_live_orchestrator_rungolivesequence", "label": "runGoLiveSequence()", "file_type": "code", "source_file": "C:\\Users\\vishw\\Desktop\\evokeeduglobal\\src\\lib\\live-stream\\go-live-orchestrator.ts", "source_location": "L56"}, {"id": "go_live_orchestrator_runendstreamsequence", "label": "runEndStreamSequence()", "file_type": "code", "source_file": "C:\\Users\\vishw\\Desktop\\evokeeduglobal\\src\\lib\\live-stream\\go-live-orchestrator.ts", "source_location": "L107"}], "edges": [{"source": "c_users_vishw_desktop_evokeeduglobal_src_lib_live_stream_go_live_orchestrator_ts", "target": "obs_client", "relation": "imports_from", "confidence": "EXTRACTED", "source_file": "C:\\Users\\vishw\\Desktop\\evokeeduglobal\\src\\lib\\live-stream\\go-live-orchestrator.ts", "source_location": "L1", "weight": 1.0}, {"source": "c_users_vishw_desktop_evokeeduglobal_src_lib_live_stream_go_live_orchestrator_ts", "target": "go_live_orchestrator_ensureyoutubebroadcast", "relation": "contains", "confidence": "EXTRACTED", "source_file": "C:\\Users\\vishw\\Desktop\\evokeeduglobal\\src\\lib\\live-stream\\go-live-orchestrator.ts", "source_location": "L7", "weight": 1.0}, {"source": "c_users_vishw_desktop_evokeeduglobal_src_lib_live_stream_go_live_orchestrator_ts", "target": "go_live_orchestrator_transitionyoutubelive", "relation": "contains", "confidence": "EXTRACTED", "source_file": "C:\\Users\\vishw\\Desktop\\evokeeduglobal\\src\\lib\\live-stream\\go-live-orchestrator.ts", "source_location": "L27", "weight": 1.0}, {"source": "c_users_vishw_desktop_evokeeduglobal_src_lib_live_stream_go_live_orchestrator_ts", "target": "go_live_orchestrator_endyoutubestream", "relation": "contains", "confidence": "EXTRACTED", "source_file": "C:\\Users\\vishw\\Desktop\\evokeeduglobal\\src\\lib\\live-stream\\go-live-orchestrator.ts", "source_location": "L37", "weight": 1.0}, {"source": "c_users_vishw_desktop_evokeeduglobal_src_lib_live_stream_go_live_orchestrator_ts", "target": "go_live_orchestrator_rungolivesequence", "relation": "contains", "confidence": "EXTRACTED", "source_file": "C:\\Users\\vishw\\Desktop\\evokeeduglobal\\src\\lib\\live-stream\\go-live-orchestrator.ts", "source_location": "L56", "weight": 1.0}, {"source": "c_users_vishw_desktop_evokeeduglobal_src_lib_live_stream_go_live_orchestrator_ts", "target": "go_live_orchestrator_runendstreamsequence", "relation": "contains", "confidence": "EXTRACTED", "source_file": "C:\\Users\\vishw\\Desktop\\evokeeduglobal\\src\\lib\\live-stream\\go-live-orchestrator.ts", "source_location": "L107", "weight": 1.0}, {"source": "go_live_orchestrator_rungolivesequence", "target": "go_live_orchestrator_ensureyoutubebroadcast", "relation": "calls", "confidence": "EXTRACTED", "source_file": "C:\\Users\\vishw\\Desktop\\evokeeduglobal\\src\\lib\\live-stream\\go-live-orchestrator.ts", "source_location": "L62", "weight": 1.0}, {"source": "go_live_orchestrator_rungolivesequence", "target": "go_live_orchestrator_transitionyoutubelive", "relation": "calls", "confidence": "EXTRACTED", "source_file": "C:\\Users\\vishw\\Desktop\\evokeeduglobal\\src\\lib\\live-stream\\go-live-orchestrator.ts", "source_location": "L104", "weight": 1.0}, {"source": "go_live_orchestrator_runendstreamsequence", "target": "go_live_orchestrator_endyoutubestream", "relation": "calls", "confidence": "EXTRACTED", "source_file": "C:\\Users\\vishw\\Desktop\\evokeeduglobal\\src\\lib\\live-stream\\go-live-orchestrator.ts", "source_location": "L120", "weight": 1.0}], "raw_calls": [{"caller_nid": "go_live_orchestrator_ensureyoutubebroadcast", "callee": "fetch", "source_file": "C:\\Users\\vishw\\Desktop\\evokeeduglobal\\src\\lib\\live-stream\\go-live-orchestrator.ts", "source_location": "L11"}, {"caller_nid": "go_live_orchestrator_ensureyoutubebroadcast", "callee": "stringify", "source_file": "C:\\Users\\vishw\\Desktop\\evokeeduglobal\\src\\lib\\live-stream\\go-live-orchestrator.ts", "source_location": "L14"}, {"caller_nid": "go_live_orchestrator_ensureyoutubebroadcast", "callee": "json", "source_file": "C:\\Users\\vishw\\Desktop\\evokeeduglobal\\src\\lib\\live-stream\\go-live-orchestrator.ts", "source_location": "L16"}, {"caller_nid": "go_live_orchestrator_transitionyoutubelive", "callee": "fetch", "source_file": "C:\\Users\\vishw\\Desktop\\evokeeduglobal\\src\\lib\\live-stream\\go-live-orchestrator.ts", "source_location": "L28"}, {"caller_nid": "go_live_orchestrator_transitionyoutubelive", "callee": "stringify", "source_file": "C:\\Users\\vishw\\Desktop\\evokeeduglobal\\src\\lib\\live-stream\\go-live-orchestrator.ts", "source_location": "L31"}, {"caller_nid": "go_live_orchestrator_transitionyoutubelive", "callee": "json", "source_file": "C:\\Users\\vishw\\Desktop\\evokeeduglobal\\src\\lib\\live-stream\\go-live-orchestrator.ts", "source_location": "L33"}, {"caller_nid": "go_live_orchestrator_endyoutubestream", "callee": "fetch", "source_file": "C:\\Users\\vishw\\Desktop\\evokeeduglobal\\src\\lib\\live-stream\\go-live-orchestrator.ts", "source_location": "L38"}, {"caller_nid": "go_live_orchestrator_endyoutubestream", "callee": "stringify", "source_file": "C:\\Users\\vishw\\Desktop\\evokeeduglobal\\src\\lib\\live-stream\\go-live-orchestrator.ts", "source_location": "L41"}, {"caller_nid": "go_live_orchestrator_endyoutubestream", "callee": "catch", "source_file": "C:\\Users\\vishw\\Desktop\\evokeeduglobal\\src\\lib\\live-stream\\go-live-orchestrator.ts", "source_location": "L44"}, {"caller_nid": "go_live_orchestrator_endyoutubestream", "callee": "json", "source_file": "C:\\Users\\vishw\\Desktop\\evokeeduglobal\\src\\lib\\live-stream\\go-live-orchestrator.ts", "source_location": "L44"}, {"caller_nid": "go_live_orchestrator_rungolivesequence", "callee": "onStep", "source_file": "C:\\Users\\vishw\\Desktop\\evokeeduglobal\\src\\lib\\live-stream\\go-live-orchestrator.ts", "source_location": "L61"}, {"caller_nid": "go_live_orchestrator_rungolivesequence", "callee": "onStep", "source_file": "C:\\Users\\vishw\\Desktop\\evokeeduglobal\\src\\lib\\live-stream\\go-live-orchestrator.ts", "source_location": "L66"}, {"caller_nid": "go_live_orchestrator_rungolivesequence", "callee": "ensureConnected", "source_file": "C:\\Users\\vishw\\Desktop\\evokeeduglobal\\src\\lib\\live-stream\\go-live-orchestrator.ts", "source_location": "L67"}, {"caller_nid": "go_live_orchestrator_rungolivesequence", "callee": "warn", "source_file": "C:\\Users\\vishw\\Desktop\\evokeeduglobal\\src\\lib\\live-stream\\go-live-orchestrator.ts", "source_location": "L69"}, {"caller_nid": "go_live_orchestrator_rungolivesequence", "callee": "onStep", "source_file": "C:\\Users\\vishw\\Desktop\\evokeeduglobal\\src\\lib\\live-stream\\go-live-orchestrator.ts", "source_location": "L75"}, {"caller_nid": "go_live_orchestrator_rungolivesequence", "callee": "isObsConfiguredForStream", "source_file": "C:\\Users\\vishw\\Desktop\\evokeeduglobal\\src\\lib\\live-stream\\go-live-orchestrator.ts", "source_location": "L76"}, {"caller_nid": "go_live_orchestrator_rungolivesequence", "callee": "catch", "source_file": "C:\\Users\\vishw\\Desktop\\evokeeduglobal\\src\\lib\\live-stream\\go-live-orchestrator.ts", "source_location": "L77"}, {"caller_nid": "go_live_orchestrator_rungolivesequence", "callee": "getObsStreamStatus", "source_file": "C:\\Users\\vishw\\Desktop\\evokeeduglobal\\src\\lib\\live-stream\\go-live-orchestrator.ts", "source_location": "L77"}, {"caller_nid": "go_live_orchestrator_rungolivesequence", "callee": "stopStreaming", "source_file": "C:\\Users\\vishw\\Desktop\\evokeeduglobal\\src\\lib\\live-stream\\go-live-orchestrator.ts", "source_location": "L83"}, {"caller_nid": "go_live_orchestrator_rungolivesequence", "callee": "onStep", "source_file": "C:\\Users\\vishw\\Desktop\\evokeeduglobal\\src\\lib\\live-stream\\go-live-orchestrator.ts", "source_location": "L89"}, {"caller_nid": "go_live_orchestrator_rungolivesequence", "callee": "pushRtmp", "source_file": "C:\\Users\\vishw\\Desktop\\evokeeduglobal\\src\\lib\\live-stream\\go-live-orchestrator.ts", "source_location": "L90"}, {"caller_nid": "go_live_orchestrator_rungolivesequence", "callee": "wait", "source_file": "C:\\Users\\vishw\\Desktop\\evokeeduglobal\\src\\lib\\live-stream\\go-live-orchestrator.ts", "source_location": "L91"}, {"caller_nid": "go_live_orchestrator_rungolivesequence", "callee": "onStep", "source_file": "C:\\Users\\vishw\\Desktop\\evokeeduglobal\\src\\lib\\live-stream\\go-live-orchestrator.ts", "source_location": "L93"}, {"caller_nid": "go_live_orchestrator_rungolivesequence", "callee": "startStreaming", "source_file": "C:\\Users\\vishw\\Desktop\\evokeeduglobal\\src\\lib\\live-stream\\go-live-orchestrator.ts", "source_location": "L94"}, {"caller_nid": "go_live_orchestrator_rungolivesequence", "callee": "warn", "source_file": "C:\\Users\\vishw\\Desktop\\evokeeduglobal\\src\\lib\\live-stream\\go-live-orchestrator.ts", "source_location": "L96"}, {"caller_nid": "go_live_orchestrator_rungolivesequence", "callee": "onStep", "source_file": "C:\\Users\\vishw\\Desktop\\evokeeduglobal\\src\\lib\\live-stream\\go-live-orchestrator.ts", "source_location": "L99"}, {"caller_nid": "go_live_orchestrator_rungolivesequence", "callee": "wait", "source_file": "C:\\Users\\vishw\\Desktop\\evokeeduglobal\\src\\lib\\live-stream\\go-live-orchestrator.ts", "source_location": "L100"}, {"caller_nid": "go_live_orchestrator_rungolivesequence", "callee": "onStep", "source_file": "C:\\Users\\vishw\\Desktop\\evokeeduglobal\\src\\lib\\live-stream\\go-live-orchestrator.ts", "source_location": "L103"}, {"caller_nid": "go_live_orchestrator_runendstreamsequence", "callee": "onStep", "source_file": "C:\\Users\\vishw\\Desktop\\evokeeduglobal\\src\\lib\\live-stream\\go-live-orchestrator.ts", "source_location": "L112"}, {"caller_nid": "go_live_orchestrator_runendstreamsequence", "callee": "stopStreaming", "source_file": "C:\\Users\\vishw\\Desktop\\evokeeduglobal\\src\\lib\\live-stream\\go-live-orchestrator.ts", "source_location": "L114"}, {"caller_nid": "go_live_orchestrator_runendstreamsequence", "callee": "onStep", "source_file": "C:\\Users\\vishw\\Desktop\\evokeeduglobal\\src\\lib\\live-stream\\go-live-orchestrator.ts", "source_location": "L119"}, {"caller_nid": "go_live_orchestrator_runendstreamsequence", "callee": "onStep", "source_file": "C:\\Users\\vishw\\Desktop\\evokeeduglobal\\src\\lib\\live-stream\\go-live-orchestrator.ts", "source_location": "L121"}]}