{"nodes": [{"id": "src_app_dashboard_tests_testsdashboard_tsx", "label": "TestsDashboard.tsx", "file_type": "code", "source_file": "src\\app\\dashboard\\tests\\TestsDashboard.tsx", "source_location": "L1"}, {"id": "testsdashboard_formatdate", "label": "formatDate()", "file_type": "code", "source_file": "src\\app\\dashboard\\tests\\TestsDashboard.tsx", "source_location": "L28"}, {"id": "testsdashboard_getstatuslabel", "label": "getStatusLabel()", "file_type": "code", "source_file": "src\\app\\dashboard\\tests\\TestsDashboard.tsx", "source_location": "L37"}, {"id": "testsdashboard_getstatusclasses", "label": "getStatusClasses()", "file_type": "code", "source_file": "src\\app\\dashboard\\tests\\TestsDashboard.tsx", "source_location": "L43"}, {"id": "testsdashboard_gettypebadgeclasses", "label": "getTypeBadgeClasses()", "file_type": "code", "source_file": "src\\app\\dashboard\\tests\\TestsDashboard.tsx", "source_location": "L53"}, {"id": "testsdashboard_statcard", "label": "StatCard()", "file_type": "code", "source_file": "src\\app\\dashboard\\tests\\TestsDashboard.tsx", "source_location": "L79"}, {"id": "testsdashboard_attemptcard", "label": "AttemptCard()", "file_type": "code", "source_file": "src\\app\\dashboard\\tests\\TestsDashboard.tsx", "source_location": "L117"}, {"id": "testsdashboard_filterattempts", "label": "filterAttempts()", "file_type": "code", "source_file": "src\\app\\dashboard\\tests\\TestsDashboard.tsx", "source_location": "L390"}], "edges": [{"source": "src_app_dashboard_tests_testsdashboard_tsx", "target": "react", "relation": "imports_from", "confidence": "EXTRACTED", "source_file": "src\\app\\dashboard\\tests\\TestsDashboard.tsx", "source_location": "L3", "weight": 1.0}, {"source": "src_app_dashboard_tests_testsdashboard_tsx", "target": "link", "relation": "imports_from", "confidence": "EXTRACTED", "source_file": "src\\app\\dashboard\\tests\\TestsDashboard.tsx", "source_location": "L4", "weight": 1.0}, {"source": "src_app_dashboard_tests_testsdashboard_tsx", "target": "recharts", "relation": "imports_from", "confidence": "EXTRACTED", "source_file": "src\\app\\dashboard\\tests\\TestsDashboard.tsx", "source_location": "L5", "weight": 1.0}, {"source": "src_app_dashboard_tests_testsdashboard_tsx", "target": "lucide_react", "relation": "imports_from", "confidence": "EXTRACTED", "source_file": "src\\app\\dashboard\\tests\\TestsDashboard.tsx", "source_location": "L12", "weight": 1.0}, {"source": "src_app_dashboard_tests_testsdashboard_tsx", "target": "card", "relation": "imports_from", "confidence": "EXTRACTED", "source_file": "src\\app\\dashboard\\tests\\TestsDashboard.tsx", "source_location": "L13", "weight": 1.0}, {"source": "src_app_dashboard_tests_testsdashboard_tsx", "target": "tabs", "relation": "imports_from", "confidence": "EXTRACTED", "source_file": "src\\app\\dashboard\\tests\\TestsDashboard.tsx", "source_location": "L14", "weight": 1.0}, {"source": "src_app_dashboard_tests_testsdashboard_tsx", "target": "progress", "relation": "imports_from", "confidence": "EXTRACTED", "source_file": "src\\app\\dashboard\\tests\\TestsDashboard.tsx", "source_location": "L15", "weight": 1.0}, {"source": "src_app_dashboard_tests_testsdashboard_tsx", "target": "badge", "relation": "imports_from", "confidence": "EXTRACTED", "source_file": "src\\app\\dashboard\\tests\\TestsDashboard.tsx", "source_location": "L16", "weight": 1.0}, {"source": "src_app_dashboard_tests_testsdashboard_tsx", "target": "button", "relation": "imports_from", "confidence": "EXTRACTED", "source_file": "src\\app\\dashboard\\tests\\TestsDashboard.tsx", "source_location": "L17", "weight": 1.0}, {"source": "src_app_dashboard_tests_testsdashboard_tsx", "target": "chart", "relation": "imports_from", "confidence": "EXTRACTED", "source_file": "src\\app\\dashboard\\tests\\TestsDashboard.tsx", "source_location": "L18", "weight": 1.0}, {"source": "src_app_dashboard_tests_testsdashboard_tsx", "target": "tests", "relation": "imports_from", "confidence": "EXTRACTED", "source_file": "src\\app\\dashboard\\tests\\TestsDashboard.tsx", "source_location": "L24", "weight": 1.0}, {"source": "src_app_dashboard_tests_testsdashboard_tsx", "target": "testsdashboard_formatdate", "relation": "contains", "confidence": "EXTRACTED", "source_file": "src\\app\\dashboard\\tests\\TestsDashboard.tsx", "source_location": "L28", "weight": 1.0}, {"source": "src_app_dashboard_tests_testsdashboard_tsx", "target": "testsdashboard_getstatuslabel", "relation": "contains", "confidence": "EXTRACTED", "source_file": "src\\app\\dashboard\\tests\\TestsDashboard.tsx", "source_location": "L37", "weight": 1.0}, {"source": "src_app_dashboard_tests_testsdashboard_tsx", "target": "testsdashboard_getstatusclasses", "relation": "contains", "confidence": "EXTRACTED", "source_file": "src\\app\\dashboard\\tests\\TestsDashboard.tsx", "source_location": "L43", "weight": 1.0}, {"source": "src_app_dashboard_tests_testsdashboard_tsx", "target": "testsdashboard_gettypebadgeclasses", "relation": "contains", "confidence": "EXTRACTED", "source_file": "src\\app\\dashboard\\tests\\TestsDashboard.tsx", "source_location": "L53", "weight": 1.0}, {"source": "src_app_dashboard_tests_testsdashboard_tsx", "target": "testsdashboard_statcard", "relation": "contains", "confidence": "EXTRACTED", "source_file": "src\\app\\dashboard\\tests\\TestsDashboard.tsx", "source_location": "L79", "weight": 1.0}, {"source": "src_app_dashboard_tests_testsdashboard_tsx", "target": "testsdashboard_attemptcard", "relation": "contains", "confidence": "EXTRACTED", "source_file": "src\\app\\dashboard\\tests\\TestsDashboard.tsx", "source_location": "L117", "weight": 1.0}, {"source": "src_app_dashboard_tests_testsdashboard_tsx", "target": "testsdashboard_filterattempts", "relation": "contains", "confidence": "EXTRACTED", "source_file": "src\\app\\dashboard\\tests\\TestsDashboard.tsx", "source_location": "L390", "weight": 1.0}, {"source": "testsdashboard_attemptcard", "target": "testsdashboard_gettypebadgeclasses", "relation": "calls", "confidence": "EXTRACTED", "source_file": "src\\app\\dashboard\\tests\\TestsDashboard.tsx", "source_location": "L133", "weight": 1.0}], "raw_calls": [{"caller_nid": "testsdashboard_formatdate", "callee": "toLocaleDateString", "source_file": "src\\app\\dashboard\\tests\\TestsDashboard.tsx", "source_location": "L30"}, {"caller_nid": "testsdashboard_filterattempts", "callee": "filter", "source_file": "src\\app\\dashboard\\tests\\TestsDashboard.tsx", "source_location": "L392"}]}