{"nodes": [{"id": "c_users_vishw_desktop_evokeeduglobal_src_proxy_ts", "label": "proxy.ts", "file_type": "code", "source_file": "C:\\Users\\vishw\\Desktop\\evokeeduglobal\\src\\proxy.ts", "source_location": "L1"}, {"id": "proxy_proxy", "label": "proxy()", "file_type": "code", "source_file": "C:\\Users\\vishw\\Desktop\\evokeeduglobal\\src\\proxy.ts", "source_location": "L4"}], "edges": [{"source": "c_users_vishw_desktop_evokeeduglobal_src_proxy_ts", "target": "server", "relation": "imports_from", "confidence": "EXTRACTED", "source_file": "C:\\Users\\vishw\\Desktop\\evokeeduglobal\\src\\proxy.ts", "source_location": "L1", "weight": 1.0}, {"source": "c_users_vishw_desktop_evokeeduglobal_src_proxy_ts", "target": "c_users_vishw_desktop_evokeeduglobal_src_utils_supabase_middleware", "relation": "imports_from", "confidence": "EXTRACTED", "source_file": "C:\\Users\\vishw\\Desktop\\evokeeduglobal\\src\\proxy.ts", "source_location": "L2", "weight": 1.0}, {"source": "c_users_vishw_desktop_evokeeduglobal_src_proxy_ts", "target": "proxy_proxy", "relation": "contains", "confidence": "EXTRACTED", "source_file": "C:\\Users\\vishw\\Desktop\\evokeeduglobal\\src\\proxy.ts", "source_location": "L4", "weight": 1.0}], "raw_calls": [{"caller_nid": "proxy_proxy", "callee": "createClient", "source_file": "C:\\Users\\vishw\\Desktop\\evokeeduglobal\\src\\proxy.ts", "source_location": "L5"}, {"caller_nid": "proxy_proxy", "callee": "getUser", "source_file": "C:\\Users\\vishw\\Desktop\\evokeeduglobal\\src\\proxy.ts", "source_location": "L8"}, {"caller_nid": "proxy_proxy", "callee": "get", "source_file": "C:\\Users\\vishw\\Desktop\\evokeeduglobal\\src\\proxy.ts", "source_location": "L14"}, {"caller_nid": "proxy_proxy", "callee": "single", "source_file": "C:\\Users\\vishw\\Desktop\\evokeeduglobal\\src\\proxy.ts", "source_location": "L17"}, {"caller_nid": "proxy_proxy", "callee": "eq", "source_file": "C:\\Users\\vishw\\Desktop\\evokeeduglobal\\src\\proxy.ts", "source_location": "L17"}, {"caller_nid": "proxy_proxy", "callee": "select", "source_file": "C:\\Users\\vishw\\Desktop\\evokeeduglobal\\src\\proxy.ts", "source_location": "L17"}, {"caller_nid": "proxy_proxy", "callee": "from", "source_file": "C:\\Users\\vishw\\Desktop\\evokeeduglobal\\src\\proxy.ts", "source_location": "L17"}, {"caller_nid": "proxy_proxy", "callee": "redirect", "source_file": "C:\\Users\\vishw\\Desktop\\evokeeduglobal\\src\\proxy.ts", "source_location": "L26"}, {"caller_nid": "proxy_proxy", "callee": "delete", "source_file": "C:\\Users\\vishw\\Desktop\\evokeeduglobal\\src\\proxy.ts", "source_location": "L27"}, {"caller_nid": "proxy_proxy", "callee": "startsWith", "source_file": "C:\\Users\\vishw\\Desktop\\evokeeduglobal\\src\\proxy.ts", "source_location": "L34"}, {"caller_nid": "proxy_proxy", "callee": "startsWith", "source_file": "C:\\Users\\vishw\\Desktop\\evokeeduglobal\\src\\proxy.ts", "source_location": "L35"}, {"caller_nid": "proxy_proxy", "callee": "startsWith", "source_file": "C:\\Users\\vishw\\Desktop\\evokeeduglobal\\src\\proxy.ts", "source_location": "L36"}, {"caller_nid": "proxy_proxy", "callee": "startsWith", "source_file": "C:\\Users\\vishw\\Desktop\\evokeeduglobal\\src\\proxy.ts", "source_location": "L37"}, {"caller_nid": "proxy_proxy", "callee": "startsWith", "source_file": "C:\\Users\\vishw\\Desktop\\evokeeduglobal\\src\\proxy.ts", "source_location": "L38"}, {"caller_nid": "proxy_proxy", "callee": "startsWith", "source_file": "C:\\Users\\vishw\\Desktop\\evokeeduglobal\\src\\proxy.ts", "source_location": "L41"}, {"caller_nid": "proxy_proxy", "callee": "set", "source_file": "C:\\Users\\vishw\\Desktop\\evokeeduglobal\\src\\proxy.ts", "source_location": "L48"}, {"caller_nid": "proxy_proxy", "callee": "redirect", "source_file": "C:\\Users\\vishw\\Desktop\\evokeeduglobal\\src\\proxy.ts", "source_location": "L49"}, {"caller_nid": "proxy_proxy", "callee": "single", "source_file": "C:\\Users\\vishw\\Desktop\\evokeeduglobal\\src\\proxy.ts", "source_location": "L55"}, {"caller_nid": "proxy_proxy", "callee": "eq", "source_file": "C:\\Users\\vishw\\Desktop\\evokeeduglobal\\src\\proxy.ts", "source_location": "L55"}, {"caller_nid": "proxy_proxy", "callee": "select", "source_file": "C:\\Users\\vishw\\Desktop\\evokeeduglobal\\src\\proxy.ts", "source_location": "L55"}, {"caller_nid": "proxy_proxy", "callee": "from", "source_file": "C:\\Users\\vishw\\Desktop\\evokeeduglobal\\src\\proxy.ts", "source_location": "L55"}, {"caller_nid": "proxy_proxy", "callee": "redirect", "source_file": "C:\\Users\\vishw\\Desktop\\evokeeduglobal\\src\\proxy.ts", "source_location": "L62"}, {"caller_nid": "proxy_proxy", "callee": "redirect", "source_file": "C:\\Users\\vishw\\Desktop\\evokeeduglobal\\src\\proxy.ts", "source_location": "L64"}]}